MANIFEST
__init__.py
manage.py
settings.py
setup.py
urls.py
djagios/README
djagios/__init__.py
djagios/config.py
djagios/import.py
djagios/release-notes.txt
djagios.egg-info/PKG-INFO
djagios.egg-info/SOURCES.txt
djagios.egg-info/dependency_links.txt
djagios.egg-info/requires.txt
djagios.egg-info/top_level.txt
djagios/common/__init__.py
djagios/common/utils.py
djagios/core/__init__.py
djagios/core/admin.py
djagios/core/exceptions.py
djagios/core/models.py
djagios/core/views.py
djagios/media/default/jquery-1.3.1.min.js
djagios/media/default/main.css
djagios/templates/default/home.html
djagios/templates/default/hostadd.html
djagios/templates/default/hostdelete.html
djagios/templates/default/hostservice.html
djagios/templates/default/hosttemplateadd.html
djagios/templates/default/index.html
djagios/templates/default/login.html