Metadata-Version: 1.0
Name: djagios
Version: 0.1
Summary: A package to help configure nagios written in Django
Home-page: http://djagios.org/
Author: Jochen Maes
Author-email: sejo@djagios.org
License: GPL2
Platform: UNKNOWN
